recipebook/__init__.py
recipebook/constants.py
recipebook/cookbook.py
recipebook/example.py
recipebook/ingredient.py
recipebook/recipe.py
recipebook/toc.py
recipebook-0.1.1.dist-info/entry_points.txt
recipebook-0.1.1.dist-info/LICENSE
recipebook-0.1.1.dist-info/WHEEL
recipebook-0.1.1.dist-info/METADATA
recipebook-0.1.1.dist-info/RECORD
